hyo.bagexplorer-0.5.7-py3.6-nspkg.pth
hyo/bagexplorer/__init__.py
hyo/bagexplorer/__main__.py
hyo/bagexplorer/explorer.py
hyo/bagexplorer/frame.py
hyo/bagexplorer/text_ctrl.py
hyo/bagexplorer/gui/__init__.py
hyo/bagexplorer/gui/mainwin.py
hyo/bagexplorer/media/BAGExplorer.icns
hyo/bagexplorer/media/BAGExplorer.ico
hyo/bagexplorer/media/BAGExplorer_128.png
hyo/bagexplorer/media/BAGExplorer_256.png
hyo/bagexplorer/media/BAGExplorer_48.png
hyo/bagexplorer/media/BAG_48.png
hyo/bagexplorer/media/favicon_32.png
hyo/bagexplorer/media/favicon_48.png
hyo/bagexplorer/media/go_back_24.png
hyo/bagexplorer/media/go_back_32.png
hyo/bagexplorer/media/go_next_24.png
hyo/bagexplorer/media/go_next_32.png
hyo/bagexplorer/media/go_top_24.png
hyo/bagexplorer/media/go_top_32.png
hyo/bagexplorer/media/go_up_24.png
hyo/bagexplorer/media/go_up_32.png
hyo/bagexplorer/media/hyo_button.png
hyo/bagexplorer/media/license.txt
hyo/bagexplorer/media/logo.png
hyo/bagexplorer/media/readme.txt
hyo/bagexplorer/media/save_24.png
hyo/bagexplorer/media/view_icon_24.png
hyo/bagexplorer/media/view_icon_32.png
hyo/bagexplorer/media/view_list_24.png
hyo/bagexplorer/media/view_list_32.png
hyo/bagexplorer/media/view_tree_24.png
hyo/bagexplorer/media/view_tree_32.png
hyo/bagexplorer/media/viz_copy_24.png
hyo/bagexplorer/media/viz_plot_24.png
hyo/bagexplorer/media/viz_plot_32.png
hyo/bagexplorer/media/xml_validate_24.png
hyo.bagexplorer-0.5.7.dist-info/METADATA
hyo.bagexplorer-0.5.7.dist-info/RECORD
hyo.bagexplorer-0.5.7.dist-info/WHEEL
hyo.bagexplorer-0.5.7.dist-info/entry_points.txt
hyo.bagexplorer-0.5.7.dist-info/namespace_packages.txt
hyo.bagexplorer-0.5.7.dist-info/top_level.txt
