Metadata-Version: 2.1
Name: hyo.bagexplorer
Version: 0.5.7
Summary: An application to browse and manage BAG files.
Home-page: https://bitbucket.org/ccomjhc/hyo_bagexplorer/
Author: Giuseppe Masetti (CCOM,UNH); Brian R. Calder (CCOM,UNH)
Author-email: gmasetti@ccom.unh.edu, brc@ccom.unh.edu
License: LGPLv3 license
Keywords: hydrography ocean mapping survey bag tools
Platform: UNKNOWN
Classifier: Development Status :: 4 - Beta
Classifier: Intended Audience :: Science/Research
Classifier: Natural Language :: English
Classifier: License :: OSI Approved :: GNU Lesser General Public License v3 (LGPLv3)
Classifier: Operating System :: OS Independent
Classifier: Programming Language :: Python
Classifier: Programming Language :: Python :: 3
Classifier: Programming Language :: Python :: 3.5
Classifier: Programming Language :: Python :: 3.6
Classifier: Topic :: Scientific/Engineering :: GIS
Classifier: Topic :: Office/Business :: Office Suites
Requires-Dist: hdf-compass
Requires-Dist: hyo.bag
